multicurrency/__init__.py
multicurrency/__init__.pyi
multicurrency/exceptions.py
multicurrency/exceptions.pyi
multicurrency/py.typed
multicurrency/pycurrency.py
multicurrency/pycurrency.pyi
multicurrency/currencies/__init__.py
multicurrency/currencies/__init__.pyi
multicurrency/currencies/afghani.py
multicurrency/currencies/afghani.pyi
multicurrency/currencies/ariary.py
multicurrency/currencies/ariary.pyi
multicurrency/currencies/baht.py
multicurrency/currencies/baht.pyi
multicurrency/currencies/balboa.py
multicurrency/currencies/balboa.pyi
multicurrency/currencies/birr.py
multicurrency/currencies/birr.pyi
multicurrency/currencies/boliviano.py
multicurrency/currencies/boliviano.pyi
multicurrency/currencies/cedi.py
multicurrency/currencies/cedi.pyi
multicurrency/currencies/colon.py
multicurrency/currencies/colon.pyi
multicurrency/currencies/crypto.py
multicurrency/currencies/crypto.pyi
multicurrency/currencies/dalasi.py
multicurrency/currencies/dalasi.pyi
multicurrency/currencies/denar.py
multicurrency/currencies/denar.pyi
multicurrency/currencies/dinar.py
multicurrency/currencies/dinar.pyi
multicurrency/currencies/dirham.py
multicurrency/currencies/dirham.pyi
multicurrency/currencies/dobra.py
multicurrency/currencies/dobra.pyi
multicurrency/currencies/dollar.py
multicurrency/currencies/dollar.pyi
multicurrency/currencies/dong.py
multicurrency/currencies/dong.pyi
multicurrency/currencies/dram.py
multicurrency/currencies/dram.pyi
multicurrency/currencies/escudo.py
multicurrency/currencies/escudo.pyi
multicurrency/currencies/euro.py
multicurrency/currencies/euro.pyi
multicurrency/currencies/florin.py
multicurrency/currencies/florin.pyi
multicurrency/currencies/forint.py
multicurrency/currencies/forint.pyi
multicurrency/currencies/franc.py
multicurrency/currencies/franc.pyi
multicurrency/currencies/fuerte.py
multicurrency/currencies/fuerte.pyi
multicurrency/currencies/gourde.py
multicurrency/currencies/gourde.pyi
multicurrency/currencies/guarani.py
multicurrency-2.1.0.dist-info/METADATA
multicurrency-2.1.0.dist-info/WHEEL
multicurrency-2.1.0.dist-info/licenses/LICENSE
multicurrency-2.1.0.dist-info/RECORD
