Metadata-Version: 2.1
Name: multicurrency
Version: 2.1.0
Summary: Currency representation library.
Project-URL: Documentation, http://fscm.github.io/multicurrency
Project-URL: Homepage, https://github.com/fscm//multicurrency
Project-URL: Source, https://github.com/fscm/multicurrency
Author: Frederico Martins
License: MIT
License-File: LICENSE
Keywords: currency,library,monetary
Classifier: Development Status :: 5 - Production/Stable
Classifier: Intended Audience :: Developers
Classifier: License :: OSI Approved :: MIT License
Classifier: Operating System :: OS Independent
Classifier: Programming Language :: Python :: 3
Classifier: Programming Language :: Python :: 3 :: Only
Classifier: Programming Language :: Python :: 3.6
Classifier: Programming Language :: Python :: 3.7
Classifier: Programming Language :: Python :: 3.8
Classifier: Programming Language :: Python :: 3.9
Classifier: Programming Language :: Python :: 3.10
Classifier: Topic :: Software Development :: Libraries
Classifier: Typing :: Typed
Requires-Python: <4,>=3.6
Provides-Extra: dev
Requires-Dist: autopep8>=1.6.0; extra == 'dev'
Requires-Dist: build>=0.8.0; extra == 'dev'
Requires-Dist: coverage[toml]>=6.4.1; extra == 'dev'
Requires-Dist: mako>=1.2.0; extra == 'dev'
Requires-Dist: mypy>=0.950; extra == 'dev'
Requires-Dist: pdoc3>=0.10.0; extra == 'dev'
Requires-Dist: pylint>=2.13.9; extra == 'dev'
Requires-Dist: pytest-cov>=3.0.0; extra == 'dev'
Requires-Dist: pytest-custom-exit-code>=0.3.0; extra == 'dev'
Requires-Dist: pytest>=7.1.2; extra == 'dev'
Requires-Dist: ruff>=0.0.282; extra == 'dev'
Requires-Dist: tabulate>=0.8.9; extra == 'dev'
Requires-Dist: twine>=4.0.0; extra == 'dev'
Requires-Dist: vermin>=1.4.0; extra == 'dev'
